test/__init__.py
test/streamcatcher.py
test/test_default.py
test/test_init.py
test/test_set.py
test/test_up.py
test/test_version_compare.py
versionner/__init__.py
versionner/__main__.py
versionner/cli.py
versionner/config.py
versionner/defaults.py
versionner/errors.py
versionner/utils.py
versionner/version.py
versionner/commands/__init__.py
versionner/commands/command.py
versionner/commands/files_management.py
versionner/commands/init.py
versionner/commands/read.py
versionner/commands/set.py
versionner/commands/tag.py
versionner/commands/up.py
versionner/vcs/__init__.py
versionner/vcs/errors.py
versionner/vcs/git.py
versionner-1.5.3.dist-info/LICENSE
versionner-1.5.3.dist-info/METADATA
versionner-1.5.3.dist-info/WHEEL
versionner-1.5.3.dist-info/entry_points.txt
versionner-1.5.3.dist-info/top_level.txt
versionner-1.5.3.dist-info/RECORD
