Metadata-Version: 2.1
Name: versionner
Version: 1.5.3
Summary: versionner helps manipulating version of the project.
Home-page: http://msztolcman.github.io/versionner/
Author: Marcin Sztolcman
Author-email: marcin@urzenia.net
License: MIT
Keywords: version management
Platform: UNKNOWN
Classifier: Development Status :: 5 - Production/Stable
Classifier: Environment :: Console
Classifier: Intended Audience :: Developers
Classifier: License :: OSI Approved :: MIT License
Classifier: Topic :: Utilities
Classifier: Topic :: Software Development
Classifier: Topic :: Software Development :: Documentation
Classifier: Topic :: Software Development :: Version Control
Classifier: Programming Language :: Python :: 3.3
Classifier: Programming Language :: Python :: 3.4
Classifier: Programming Language :: Python :: 3.5
Classifier: Programming Language :: Python :: 3.6
Classifier: Programming Language :: Python :: 3.7
Requires-Dist: argparse
Requires-Dist: semver
